Workbook

Sheet Dashboard
A1: ROADMAP 500K BERSIH / HARI — PAK HUSNUL
A2: 90-Day Revenue Operating System | Hero Product: ModulAjar + BuatSoal | Organic-first + Affiliate
A4: INPUT & ASUMSI — EDIT JIKA BERUBAH | D4: HERO PRODUCT & ASUMSI MIX
A5: Target bersih / hari | B5: 500000 | D5: Produk | E5: Harga | F5: Mix | G5: Weighted
A6: Hari / bulan | B6: 30 | D6: ModulAjar Online | E6: 149000 | F6: 0.4 | G6: =E6*F6
A7: Langganan AI / produk / bulan | B7: 350000 | D7: BuatSoal Online Pro | E7: 149000 | F7: 0.4 | G7: =E7*F7
A8: Jumlah hero product | B8: 2 | D8: BuatSoal Online Max | E8: 249000 | F8: 0.2 | G8: =E8*F8
A9: Domain / produk / tahun | B9: 250000 | D9: TOTAL / AOV | F9: 1 | G9: =SUM(G6:G8)
A10: Komisi affiliate | B10: 0.4
A11: Asumsi porsi gross dari affiliate | B11: 0.25
A12: Weighted AOV | B12: =G9 | D12: TARGET PER FASE
D13: Fase | E13: Hari | F13: Net / Hari | G13: Net 30 Hari | H13: Gross / Minggu
A14: TARGET EKONOMI | D14: Fase 1 | E14: Hari 1–30 | F14: 350000 | G14: =F14*$B$6 | H14: =((F14*7)+($B$16/$B$6*7))/$B$17
A15: Target bersih / bulan | B15: =B5*B6 | D15: Fase 2 | E15: Hari 31–60 | F15: 425000 | G15: =F15*$B$6 | H15: =((F15*7)+($B$16/$B$6*7))/$B$17
A16: Fixed cost / bulan | B16: =ROUND(B7*B8+(B9*B8/12),0) | D16: Fase 3 | E16: Hari 61–90 | F16: 500000 | G16: =F16*$B$6 | H16: =((F16*7)+($B$16/$B$6*7))/$B$17
A17: Retained factor setelah affiliate | B17: =1-(B10*B11)
A18: Target gross / bulan | B18: =ROUND((B15+B16)/B17,0) | D18: ATURAN STRATEGIS
A19: Target gross / minggu | B19: =ROUND((B18/B6)*7,0) | D19: 1 | E19: 80% marketing effort → ModulAjar + BuatSoal; produk lain = bonus/cross-sell/campaign khusus.
A20: Kebutuhan transaksi / bulan | B20: =B18/B12 | D20: 2 | E20: Jangan tambah kalender YouTube di workbook ini. Semua YouTube mengikuti file “YouTube Growth Plan — Pak Husnul — 90 Hari”.
A21: Kebutuhan transaksi / hari | B21: =B20/B6 | D21: 3 | E21: Post & Cuan tetap source of truth harian. Workbook ini hanya roll-up mingguan + keputusan revenue.
A22: Kebutuhan transaksi / minggu | B22: =B21*7 | D22: 4 | E22: Promo diskon hanya event tertentu. Default campaign = harga normal + value/bonus/proof.
D23: 5 | E23: Target utama = rolling 30 hari / mingguan; bukan memaksa Rp500K masuk tepat setiap hari.

Sheet START HERE
A1: PAK HUSNUL — MASTER CONTENT OPERATING SYSTEM | 90 HARI
A3: Tujuan | B3: Mengintegrasikan Roadmap 500K/hari + YouTube Growth + daily content ModulAjar/BuatSoal + Sumber Belajar + Apps + WhatsApp menjadi satu kalender.
A4: Prinsip | B4: Jangan menambah pekerjaan. 1 Weekly Theme → Revenue + YouTube + Social + WA + Sumber Belajar + App.
A5: Source of truth | B5: Revenue: Roadmap 500K | YouTube: YouTube Growth Plan | Daily product content: TikTok + Threads | Membership: Sumber Belajar
A6: Prioritas | B6: P0 Revenue daily + committed YouTube → P1 WA nurturing + repurpose → P2 signature membership → P3 eksperimen
A7: Daily product rule | B7: Minimal 1 konten/hari untuk ModulAjar Online atau BuatSoal Online. Kalender ini mengatur tema/arah, bukan menggantikan workflow posting Anda.
A8: WhatsApp | B8: Guru Mahir AI = public/warm pool. Aidukasi = closed/warmer pool.
A9: Sumber Belajar | B9: Mayoritas derived content dari YouTube, product content, apps, dan live. Jangan membuat kalender produksi terpisah.
A11: Workbook tabs
A12: MASTER CALENDAR | B12: Satu baris per hari; kalender utama.
A13: WEEKLY CLUSTERS | B13: 13 tema mingguan yang menyatukan revenue + YouTube + membership.
A14: SUMBER BELAJAR | B14: Backlog/production schedule untuk 6 menu dan tier.
A15: DAILY PRODUCT | B15: Tracker harian ModulAjar/BuatSoal di TikTok + Threads.
A16: YT ALIGNMENT | B16: Jadwal YouTube dari workbook asli, tanpa menambah upload.
A17: WA DISTRIBUTION | B17: Ritme Guru Mahir AI + Aidukasi.
A18: KPI DASHBOARD | B18: KPI lintas mesin.
A19: SOURCE REVENUE | B19: Salinan 90-day revenue roadmap.
A20: SOURCE YOUTUBE | B20: Salinan 90-day YouTube roadmap.

Sheet CONFIG
A1: CONFIG & OPERATING RULES
A3: Control Date | B3: 46299
A4: Revenue Hero Product | B4: ModulAjar Online + BuatSoal Online
A5: Daily Social Minimum | B5: >= 1 post/day
A6: Social Channels | B6: TikTok + Threads
A7: YouTube Cadence | B7: Tue Long-form | Wed Short | Fri Long-form | Sat Short | Sun Live
A8: WA Public Pool | B8: Guru Mahir AI
A9: WA Closed Pool | B9: Aidukasi
A10: Sumber Belajar Automated | B10: Cron: Bank Prompt + AI Skills, 3x/day
A11: Sumber Belajar Manual | B11: Signature/deep-dive 1 per week max
A12: Default Content Repurpose | B12: YouTube/Product/App/Live → Prompt/Skill/Tutorial/Template/WA
A13: Do Not Do | B13: Jangan membuat kalender YouTube tambahan; jangan membuat Sumber Belajar sebagai pekerjaan terpisah.
A14: Start Date | B14: 46300
A15: Plan End Date | B15: 46389

Sheet WEEKLY CLUSTERS
A1: Week | B1: Mulai | C1: Selesai | D1: Revenue Focus | E1: Primary Campaign | F1: YouTube Focus | G1: YT Long-form #1 | H1: YT Long-form #2 | I1: YT Live | J1: Membership Cluster | K1: Sumber Belajar Outputs | L1: Primary CTA | M1: WA Focus | N1: Revenue Target
A2: 1 | B2: 46300 | C2: 46306 | D2: Reset & tracking | E2: Post & Cuan reset + segmentasi | F2: Reset positioning + bangun cluster Gemini/Deploy | G2: Gemini Canvas ke Netlify: Cara Deploy Website Sampai Online | H2: Saya Bikin Aplikasi Tanpa Bisa Coding — Ini Workflow Saya | I2: Bikin Web App dari Nol dengan AI + Deploy | J2: Reset & Tracking | K2: Content library audit + tagging | — | L2: Contextual CTA | M2: Tidak jualan keras 18 Agu; rapikan segment & next campaign. | N2: 2450000
A3: 2 | B3: 46307 | C3: 46313 | D3: Cross-sell #1 | E3: ModulAjar → BuatSoal | F3: Custom GPT cluster | G3: Cara Membuat Custom GPT dari Nol — Sampai Bisa Dipakai | H3: 7 Kesalahan Saat Membuat Custom GPT | I3: Bikin Custom GPT untuk Membuat Soal | J3: Cross-sell ModulAjar → BuatSoal | K3: Cross-sell prompt/checklist | Premium workflow | L3: ModulAjar Online | M3: WA sequence 4–5 sentuhan: edukasi → demo → proof → offer. | N3: 2450000
A4: 3 | B4: 46314 | C4: 46320 | D4: Acquisition sprint | E4: Lead magnet masuk WA | F4: PRD → aplikasi | G4: Dari Ide → PRD → Aplikasi dengan AI | H4: Tools AI Pembuat PRD: Saya Tes untuk Project Nyata | I4: Dari Ide Kosong Jadi PRD + Prototype | J4: Lead Magnet Acquisition | K4: High-intent lead magnet | — | L4: Contextual CTA | M4: TikTok/Threads → lead magnet → Guru Mahir AI. | N4: 2450000
A5: 4 | B5: 46321 | C5: 46327 | D5: Upgrade campaign | E5: BuatSoal Pro → Max | F5: Guru Bikin Aplikasi dimulai | G5: Saya Bikin Aplikasi Absensi Siswa Pakai AI | H5: Google Sheets Jadi Aplikasi dalam 30 Menit | I5: Bikin Aplikasi Absensi Siswa dari Nol | J5: BuatSoal Pro → Max | K5: Assessment workflow resource | Premium assessment workflow | L5: BuatSoal Online | M5: FAQ + demo pembeda Pro vs Max + CTA upgrade. | N5: 2450000
A6: 5 | B6: 46328 | C6: 46334 | D6: Lead Magnet Engine | E6: 2 jalur lead magnet | F6: Scale cluster pemenang + nilai siswa | G6: Saya Bikin Aplikasi Nilai Siswa Pakai AI | H6: Cara Update Website Netlify Tanpa Ganti Link | I6: Bikin Aplikasi Nilai + Rekap Otomatis | J6: Lead Magnet Engine | K6: 2 lead-magnet tracks | — | L6: Contextual CTA | M6: Target +150–200 lead baru/bulan mulai fase ini. | N6: 2975000
A7: 6 | B7: 46335 | C7: 46341 | D7: Affiliate Sprint #1 | E7: Hero Week: ModulAjar | F7: Gemini Gems + workflow guru | G7: Cara Membuat Gemini Gems yang Benar | H7: Saya Bikin AI Pembuat Soal dengan Gemini Gems | I7: Bikin Asisten Soal Guru dengan Gemini | J7: Hero Week: ModulAjar | K7: Teacher planning resource cluster | VIP teacher workflow | L7: ModulAjar Online | M7: WA grup affiliate: 1 briefing utama + 1 follow-up hasil. | N7: 2975000
A8: 7 | B8: 46342 | C8: 46348 | D8: Normal-price campaign | E8: BuatSoal Online | F8: Deploy + domain | G8: Cara Pasang Custom Domain di Netlify untuk Pemula | H8: Netlify vs Vercel: Mana Paling Mudah untuk Pemula? | I8: Web AI → Deploy → Custom Domain LIVE | J8: Hero Week: BuatSoal | K8: Assessment resource cluster | VIP assessment architect | L8: BuatSoal Online | M8: Lead magnet BuatSoal + case study + offer. | N8: 2975000
A9: 8 | B9: 46349 | C9: 46355 | D9: Normal-price campaign | E9: ModulAjar Online | F9: AI productivity + education crossover | G9: Dari RPP Jadi PowerPoint dengan AI | H9: 7 Prompt AI yang Menghemat Pekerjaan Guru | I9: Bikin Media Pembelajaran dari RPP | J9: AI untuk Perencanaan Pembelajaran | K9: RPP → PPT Prompt + AI Skill + Cheatsheet | Premium RPP→Presentation | L9: ModulAjar Online | M9: Nurture lead baru + proof existing customer. | N9: 2975000
A10: 9 | B10: 46356 | C10: 46362 | D10: Scale winner | E10: Scale channel/campaign terbaik | F10: Serial Guru Bikin Aplikasi | G10: Bikin Aplikasi Kas Kelas dengan AI | H10: Bikin Aplikasi Jurnal Mengajar dengan AI | I10: Bikin Kas Kelas + Dashboard | J10: Guru Bikin Aplikasi | K10: Kas Kelas/Jurnal + App Builder resources | Premium Teacher App Builder | L10: Contextual CTA | M10: Kurangi aktivitas yang tidak menghasilkan lead/sales. | N10: 3500000
A11: 10 | B11: 46363 | C11: 46369 | D11: Affiliate Sprint #2 | E11: Hero Week: BuatSoal | F11: Build in public produk nyata | G11: Saya Bikin PosterEdu: Dari Masalah Jadi Aplikasi | H11: Kenapa Aplikasi AI Saya Lambat? Ini Kesalahannya | I11: Audit + Perbaiki Aplikasi AI yang Lambat | J11: Build in Public Produk Nyata | K11: PosterEdu/App performance workflow | VIP implementation blueprint | L11: BuatSoal Online | M11: WA affiliate fokus objection handling + proof. | N11: 3500000
A12: 11 | B12: 46370 | C12: 46376 | D12: Cross-sell #2 | E12: BuatSoal → ModulAjar | F12: Marketplace / produk digital | G12: Dari Aplikasi Jadi Produk Digital: Workflow Saya | H12: Saya Tambahkan Marketplace ke Aplikasi Guru | I12: Build Marketplace Sederhana dengan AI | J12: Aplikasi → Produk Digital | K12: Productization/marketplace templates | Premium product system | L12: ModulAjar Online | M12: Segmented WA/DM; hindari broadcast ke semua orang. | N12: 3500000
A13: 12 | B13: 46377 | C13: 46383 | D13: Backend validation | E13: Membership 9K + produk pendamping | F13: Perbandingan tools berintent tinggi | G13: ChatGPT vs Gemini untuk Bikin Aplikasi: Saya Tes | H13: Lovable vs Google Apps Script + AI: Pilih Mana? | I13: Battle Build: 2 Tools, 1 Aplikasi | J13: AI Tools Comparison | K13: Decision framework + tool workflow | VIP build framework | L13: Contextual CTA | M13: Target 25–50 member aktif, tapi jangan korbankan hero-product sales. | N13: 3500000
A14: 13 | B14: 46384 | C14: 46390 | D14: 90-day scale decision | E14: 500K/day run-rate | F14: 90-day recap + next season | G14: 90 Hari Membangun Channel AI: Apa yang Berhasil? | H14: Saya Bikin Aplikasi Wali Kelas Tanpa Jadi Programmer | I14: Final Build: Aplikasi Wali Kelas | J14: 90-Day Recap & Next Season | K14: Best-of library + Wali Kelas app cluster | VIP next-season workshop | L14: Contextual CTA | M14: Pilih 1–2 engine untuk scale berikutnya; hentikan aktivitas low-ROI. | N14: 3500000

Sheet MASTER CALENDAR
A1: Date | B1: Day | C1: Week | D1: Weekly Theme | E1: Revenue Focus | F1: Daily Product Content | G1: YouTube | H1: Sumber Belajar / Repurpose | I1: Apps | J1: WA / Distribution | K1: Primary CTA | L1: Priority | M1: Status | N1: Notes
A2: 46300 | B2: Monday | C2: 1 | D2: Reset & Tracking | E2: Post & Cuan reset + segmentasi | F2: ModulAjar Online / BuatSoal Online — min. 1 konten (pilih sesuai angle) | G2: — | H2: — | I2: — | J2: Edukasi / problem awareness | K2: pakhusnul.id / contextual product | L2: P0 | M2: Past | N2: Do not add new long-form/live. Repurpose existing source asset.
A3: 46301 | B3: Tuesday | C3: 1 | D3: Reset & Tracking | E3: Post & Cuan reset + segmentasi | F3: ModulAjar Online / BuatSoal Online — min. 1 konten (pilih sesuai angle) | G3: Long-form #1: Gemini Canvas ke Netlify: Cara Deploy Website Sampai Online | H3: — | I3: — | J3: Share YT / proof / discussion | K3: pakhusnul.id / contextual product | L3: P0 | M3: Past | N3: Committed YouTube slot from source plan.
A4: 46302 | B4: Wednesday | C4: 1 | D4: Reset & Tracking | E4: Post & Cuan reset + segmentasi | F4: ModulAjar Online / BuatSoal Online — min. 1 konten (pilih sesuai angle) | G4: Short #1 (repurpose long-form) | H4: FREE / derived resource: 1 public/free resource cleanup | I4: — | J4: Free resource / lead magnet | K4: pakhusnul.id / contextual product | L4: P0 | M4: Past | N4: Do not add new long-form/live. Repurpose existing source asset.
A5: 46303 | B5: Thursday | C5: 1 | D5: Reset & Tracking | E5: Post & Cuan reset + segmentasi | F5: ModulAjar Online / BuatSoal Online — min. 1 konten (pilih sesuai angle) | G5: — | H5: AI Skill / Premium: — | I5: — | J5: Deep education + contextual offer | K5: pakhusnul.id / contextual product | L5: P0 | M5: Past | N5: Do not add new long-form/live. Repurpose existing source asset.
A6: 46304 | B6: Friday | C6: 1 | D6: Reset & Tracking | E6: Post & Cuan reset + segmentasi | F6: ModulAjar Online / BuatSoal Online — min. 1 konten (pilih sesuai angle) | G6: Long-form #2: Saya Bikin Aplikasi Tanpa Bisa Coding — Ini Workflow Saya | H6: — | I6: — | J6: Share YT + case/proof | K6: pakhusnul.id / contextual product | L6: P0 | M6: Past | N6: Committed YouTube slot from source plan.
A7: 46305 | B7: Saturday | C7: 1 | D7: Reset & Tracking | E7: Post & Cuan reset + segmentasi | F7: ModulAjar Online / BuatSoal Online — min. 1 konten (pilih sesuai angle) | G7: Short #2 (repurpose long-form) | H7: Template / Others / App asset dari weekly cluster | I7: — | J7: Resource + reminder | K7: pakhusnul.id / contextual product | L7: P0 | M7: Past | N7: Do not add new long-form/live. Repurpose existing source asset.
A8: 46306 | B8: Sunday | C8: 1 | D8: Reset & Tracking | E8: Post & Cuan reset + segmentasi | F8: ModulAjar Online / BuatSoal Online — min. 1 konten (pilih sesuai angle) | G8: LIVE: Bikin Web App dari Nol dengan AI + Deploy | H8: Capture ideas from LIVE → backlog minggu berikutnya | I8: — | J8: Live reminder + follow-up | K8: pakhusnul.id / contextual product | L8: P0 | M8: Past | N8: Committed YouTube slot from source plan.
A9: 46307 | B9: Monday | C9: 2 | D9: Cross-sell ModulAjar → BuatSoal | E9: ModulAjar → BuatSoal | F9: ModulAjar → BuatSoal — min. 1 konten TikTok/Threads | G9: — | H9: — | I9: — | J9: Edukasi / problem awareness | K9: pakhusnul.id / contextual product | L9: P0 | M9: Past | N9: Do not add new long-form/live. Repurpose existing source asset.
A10: 46308 | B10: Tuesday | C10: 2 | D10: Cross-sell ModulAjar → BuatSoal | E10: ModulAjar → BuatSoal | F10: ModulAjar → BuatSoal — min. 1 konten TikTok/Threads | G10: Long-form #1: Cara Membuat Custom GPT dari Nol — Sampai Bisa Dipakai | H10: — | I10: — | J10: Share YT / proof / discussion | K10: pakhusnul.id / contextual product | L10: P0 | M10: Past | N10: Committed YouTube slot from source plan.
A11: 46309 | B11: Wednesday | C11: 2 | D11: Cross-sell ModulAjar → BuatSoal | E11: ModulAjar → BuatSoal | F11: ModulAjar → BuatSoal — min. 1 konten TikTok/Threads | G11: Short #1 (repurpose long-form) | H11: FREE / derived resource: Cross-sell checklist | I11: — | J11: Free resource / lead magnet | K11: pakhusnul.id / contextual product | L11: P0 | M11: Past | N11: Do not add new long-form/live. Repurpose existing source asset.
A12: 46310 | B12: Thursday | C12: 2 | D12: Cross-sell ModulAjar → BuatSoal | E12: ModulAjar → BuatSoal | F12: ModulAjar → BuatSoal — min. 1 konten TikTok/Threads | G12: — | H12: AI Skill / Premium: Premium workflow | I12: — | J12: Deep education + contextual offer | K12: pakhusnul.id / contextual product | L12: P0 | M12: Past | N12: Do not add new long-form/live. Repurpose existing source asset.
A13: 46311 | B13: Friday | C13: 2 | D13: Cross-sell ModulAjar → BuatSoal | E13: ModulAjar → BuatSoal | F13: ModulAjar → BuatSoal — min. 1 konten TikTok/Threads | G13: Long-form #2: 7 Kesalahan Saat Membuat Custom GPT | H13: — | I13: — | J13: Share YT + case/proof | K13: pakhusnul.id / contextual product | L13: P0 | M13: Past | N13: Committed YouTube slot from source plan.
... A92: 46390 | B92: Sunday | C92: 13 | D92: 90-Day Recap & Next Season | E92: 500K/day run-rate | F92: ModulAjar Online / BuatSoal Online — min. 1 konten (pilih sesuai angle) | G92: LIVE: Final Build: Aplikasi Wali Kelas | H92: Capture ideas from LIVE → backlog minggu berikutnya | I92: Aplikasi Wali Kelas — final build | J92: Live reminder + follow-up | K92: pakhusnul.id / contextual product | L92: P0 | M92: Planned | N92: Committed YouTube slot from source plan.

Sheet SUMBER BELAJAR
A1: ID | B1: Week | C1: Target Date | D1: Source Asset | E1: Menu | F1: Content Title / Working Idea | G1: Tier | H1: Source Type | I1: Production Effort | J1: CTA | K1: Status | L1: Notes
A2: SB-W01-01 | B2: 1 | C2: 46302 | D2: Derived from YT/Product | E2: Bank Prompt | F2: 1 public/free resource cleanup | G2: FREE | H2: Repurpose | I2: Low | J2: Free Member / pakhusnul.id | K2: Planned | L2: Diturunkan dari weekly theme; tidak membuat topik terpisah.
A3: SB-W01-02 | B3: 1 | C3: 46303 | D3: Derived / curated | E3: AI Skills | F3: AI Skill — Reset & Tracking | G3: PREMIUM | H3: Repurpose/Curated | I3: Medium | J3: Upgrade Premium | K3: Planned | L3: Cron dapat memasok volume; admin memilih skill yang paling relevan.
A4: SB-W01-03 | B4: 1 | C4: 46305 | D4: YouTube/Product/App | E4: Others | F4: Template / Cheatsheet — Reset & Tracking | G4: FREE | H4: Repurpose | I4: Low | J4: Free Member | K4: Planned | L4: Gunakan output yang sudah dibuat; jangan menambah produksi besar.
A5: SB-W02-01 | B5: 2 | C5: 46309 | D5: Derived from YT/Product | E5: Bank Prompt | F5: Cross-sell checklist | G5: FREE | H5: Repurpose | I5: Low | J5: Free Member / pakhusnul.id | K5: Planned | L5: Diturunkan dari weekly theme; tidak membuat topik terpisah.
A6: SB-W02-02 | B6: 2 | C6: 46310 | D6: Derived / curated | E6: AI Skills | F6: AI Skill — Cross-sell ModulAjar → BuatSoal | G6: PREMIUM | H6: Repurpose/Curated | I6: Medium | J6: Upgrade Premium | K6: Planned | L6: Cron dapat memasok volume; admin memilih skill yang paling relevan.
A7: SB-W02-03 | B7: 2 | C7: 46312 | D7: YouTube/Product/App | E7: Others | F7: Template / Cheatsheet — Cross-sell ModulAjar → BuatSoal | G7: FREE | H7: Repurpose | I7: Low | J7: Free Member | K7: Planned | L7: Gunakan output yang sudah dibuat; jangan menambah produksi besar.
A8: SB-W03-01 | B8: 3 | C8: 46316 | D8: Derived from YT/Product | E8: Bank Prompt | F8: Lead magnet + landing resource | G8: FREE | H8: Repurpose | I8: Low | J8: Free Member / pakhusnul.id | K8: Planned | L8: Diturunkan dari weekly theme; tidak membuat topik terpisah.
A9: SB-W03-02 | B9: 3 | C9: 46317 | D9: Derived / curated | E9: AI Skills | F9: AI Skill — Lead Magnet Acquisition | G9: PREMIUM | H9: Repurpose/Curated | I9: Medium | J9: Upgrade Premium | K9: Planned | L9: Cron dapat memasok volume; admin memilih skill yang paling relevan.
A10: SB-W03-03 | B10: 3 | C10: 46319 | D10: YouTube/Product/App | E10: Others | F10: Template / Cheatsheet — Lead Magnet Acquisition | G10: FREE | H10: Repurpose | I10: Low | J10: Free Member | K10: Planned | L10: Gunakan output yang sudah dibuat; jangan menambah produksi besar.
A11: SB-W04-01 | B11: 4 | C11: 46323 | D11: Derived from YT/Product | E11: Bank Prompt | F11: Assessment prompt | G11: FREE | H11: Repurpose | I11: Low | J11: Free Member / pakhusnul.id | K11: Planned | L11: Diturunkan dari weekly theme; tidak membuat topik terpisah.
A12: SB-W04-02 | B12: 4 | C12: 46324 | D12: Derived / curated | E12: AI Skills | F12: AI Skill — BuatSoal Pro → Max | G12: PREMIUM | H12: Repurpose/Curated | I12: Medium | J12: Upgrade Premium | K12: Planned | L12: Cron dapat memasok volume; admin memilih skill yang paling relevan.
A13: SB-W04-03 | B13: 4 | C13: 46326 | D13: YouTube/Product/App | E13: Others | F13: Template / Cheatsheet — BuatSoal Pro → Max | G13: FREE | H13: Repurpose | I13: Low | J13: Free Member | K13: Planned | L13: Gunakan output yang sudah dibuat; jangan menambah produksi besar.
... A51: SB-W13-05 | B51: 13 | C51: 46390 | D51: App / Build | E51: Apps | F51: App Resource — 90-Day Recap & Next Season | G51: PUBLIC/FREE | H51: App | I51: Medium | J51: Try App / Join Member | K51: Planned | L51: App dapat punya akses tier sendiri.

Sheet DAILY PRODUCT
A1: Date | B1: Week | C1: Campaign Focus | D1: Recommended Product | E1: TikTok/Threads Minimum | F1: Content Angle | G1: CTA | H1: Status | I1: Published? | J1: Link / Notes
A2: 46300 | B2: 1 | C2: Post & Cuan reset + segmentasi | D2: ModulAjar Online / BuatSoal Online | E2: >= 1 post | F2: Pain point | G2: Pilih hero product sesuai angle | H2: Planned
A3: 46301 | B3: 1 | C3: Post & Cuan reset + segmentasi | D3: ModulAjar Online / BuatSoal Online | E3: >= 1 post | F3: Education | G3: Pilih hero product sesuai angle | H3: Planned
A4: 46302 | B4: 1 | C4: Post & Cuan reset + segmentasi | D4: ModulAjar Online / BuatSoal Online | E4: >= 1 post | F4: Demo | G4: Pilih hero product sesuai angle | H4: Planned
A5: 46303 | B5: 1 | C5: Post & Cuan reset + segmentasi | D5: ModulAjar Online / BuatSoal Online | E5: >= 1 post | F5: Use case | G5: Pilih hero product sesuai angle | H5: Planned
A6: 46304 | B6: 1 | C6: Post & Cuan reset + segmentasi | D6: ModulAjar Online / BuatSoal Online | E6: >= 1 post | F6: Feature | G6: Pilih hero product sesuai angle | H6: Planned
A7: 46305 | B7: 1 | C7: Post & Cuan reset + segmentasi | D7: ModulAjar Online / BuatSoal Online | E7: >= 1 post | F7: Proof/Testimonial | G7: Pilih hero product sesuai angle | H7: Planned
A8: 46306 | B8: 1 | C8: Post & Cuan reset + segmentasi | D8: ModulAjar Online / BuatSoal Online | E8: >= 1 post | F8: Offer/CTA | G8: Pilih hero product sesuai angle | H8: Planned
A9: 46307 | B9: 2 | C9: ModulAjar → BuatSoal | D9: ModulAjar Online | E9: >= 1 post | F9: Pain point | G9: ModulAjar Online | H9: Planned
A10: 46308 | B10: 2 | C10: ModulAjar → BuatSoal | D10: ModulAjar Online | E10: >= 1 post | F10: Education | G10: ModulAjar Online | H10: Planned
A11: 46309 | B11: 2 | C11: ModulAjar → BuatSoal | D11: ModulAjar Online | E11: >= 1 post | F11: Demo | G11: ModulAjar Online | H11: Planned
A12: 46310 | B12: 2 | C12: ModulAjar → BuatSoal | D12: ModulAjar Online | E12: >= 1 post | F12: Use case | G12: ModulAjar Online | H12: Planned
A13: 46311 | B13: 2 | C13: ModulAjar → BuatSoal | D13: ModulAjar Online | E13: >= 1 post | F13: Feature | G13: ModulAjar Online | H13: Planned
... A92: 46390 | B92: 13 | C92: 500K/day run-rate | D92: ModulAjar Online / BuatSoal Online | E92: >= 1 post | F92: Offer/CTA | G92: Pilih hero product sesuai angle | H92: Planned

Sheet YT ALIGNMENT
A1: Week | B1: Start | C1: End | D1: Focus | E1: Long-form #1 | F1: Long-form #2 | G1: Live | H1: Shorts | I1: Watch Target | J1: Review | K1: Integration Rule
A2: 1 | B2: 46300 | C2: 46306 | D2: Reset positioning + bangun cluster Gemini/Deploy | E2: Gemini Canvas ke Netlify: Cara Deploy Website Sampai Online | F2: Saya Bikin Aplikasi Tanpa Bisa Coding — Ini Workflow Saya | G2: Bikin Web App dari Nol dengan AI + Deploy | H2: 2 | I2: 25 | J2: Cek CTR + retention 30 detik | K2: LOCKED: no additional long-form/live from revenue or membership calendar. Repurpose only.
A3: 2 | B3: 46307 | C3: 46313 | D3: Custom GPT cluster | E3: Cara Membuat Custom GPT dari Nol — Sampai Bisa Dipakai | F3: 7 Kesalahan Saat Membuat Custom GPT | G3: Bikin Custom GPT untuk Membuat Soal | H3: 2 | I3: 30 | J3: Bandingkan search vs browse | K3: LOCKED: no additional long-form/live from revenue or membership calendar. Repurpose only.
A4: 3 | B4: 46314 | C4: 46320 | D4: PRD → aplikasi | E4: Dari Ide → PRD → Aplikasi dengan AI | F4: Tools AI Pembuat PRD: Saya Tes untuk Project Nyata | G4: Dari Ide Kosong Jadi PRD + Prototype | H4: 2 | I4: 35 | J4: Catat pertanyaan audience | K4: LOCKED: no additional long-form/live from revenue or membership calendar. Repurpose only.
A5: 4 | B5: 46321 | C5: 46327 | D5: Guru Bikin Aplikasi dimulai | E5: Saya Bikin Aplikasi Absensi Siswa Pakai AI | F5: Google Sheets Jadi Aplikasi dalam 30 Menit | G5: Bikin Aplikasi Absensi Siswa dari Nol | H5: 2 | I5: 40 | J5: Pilih 2 cluster terbaik bulan 1 | K5: LOCKED: no additional long-form/live from revenue or membership calendar. Repurpose only.
A6: 5 | B6: 46328 | C6: 46334 | D6: Scale cluster pemenang + nilai siswa | E6: Saya Bikin Aplikasi Nilai Siswa Pakai AI | F6: Cara Update Website Netlify Tanpa Ganti Link | G6: Bikin Aplikasi Nilai + Rekap Otomatis | H6: 2 | I6: 50 | J6: Update thumbnail video CTR rendah | K6: LOCKED: no additional long-form/live from revenue or membership calendar. Repurpose only.
A7: 6 | B7: 46335 | C7: 46341 | D7: Gemini Gems + workflow guru | E7: Cara Membuat Gemini Gems yang Benar | F7: Saya Bikin AI Pembuat Soal dengan Gemini Gems | G7: Bikin Asisten Soal Guru dengan Gemini | H7: 2 | I7: 60 | J7: Perkuat end-screen chain | K7: LOCKED: no additional long-form/live from revenue or membership calendar. Repurpose only.
A8: 7 | B8: 46342 | C8: 46348 | D8: Deploy + domain | E8: Cara Pasang Custom Domain di Netlify untuk Pemula | F8: Netlify vs Vercel: Mana Paling Mudah untuk Pemula? | G8: Web AI → Deploy → Custom Domain LIVE | H8: 2 | I8: 70 | J8: Cek suggested traffic antarvideo | K8: LOCKED: no additional long-form/live from revenue or membership calendar. Repurpose only.
A9: 8 | B9: 46349 | C9: 46355 | D9: AI productivity + education crossover | E9: Dari RPP Jadi PowerPoint dengan AI | F9: 7 Prompt AI yang Menghemat Pekerjaan Guru | G9: Bikin Media Pembelajaran dari RPP | H9: 2 | I9: 80 | J9: Review 8 minggu: stop topik lemah | K9: LOCKED: no additional long-form/live from revenue or membership calendar. Repurpose only.
A10: 9 | B10: 46356 | C10: 46362 | D10: Serial Guru Bikin Aplikasi | E10: Bikin Aplikasi Kas Kelas dengan AI | F10: Bikin Aplikasi Jurnal Mengajar dengan AI | G10: Bikin Kas Kelas + Dashboard | H10: 2 | I10: 95 | J10: Optimasi playlist series | K10: LOCKED: no additional long-form/live from revenue or membership calendar. Repurpose only.
A11: 10 | B11: 46363 | C11: 46369 | D11: Build in public produk nyata | E11: Saya Bikin PosterEdu: Dari Masalah Jadi Aplikasi | F11: Kenapa Aplikasi AI Saya Lambat? Ini Kesalahannya | G11: Audit + Perbaiki Aplikasi AI yang Lambat | H11: 2 | I11: 110 | J11: Cari peak retention untuk format authority | K11: LOCKED: no additional long-form/live from revenue or membership calendar. Repurpose only.
A12: 11 | B12: 46370 | C12: 46376 | D12: Marketplace / produk digital | E12: Dari Aplikasi Jadi Produk Digital: Workflow Saya | F12: Saya Tambahkan Marketplace ke Aplikasi Guru | G12: Build Marketplace Sederhana dengan AI | H12: 2 | I12: 125 | J12: Periksa subscriber gained/video | K12: LOCKED: no additional long-form/live from revenue or membership calendar. Repurpose only.
A13: 12 | B13: 46377 | C13: 46383 | D13: Perbandingan tools berintent tinggi | E13: ChatGPT vs Gemini untuk Bikin Aplikasi: Saya Tes | F13: Lovable vs Google Apps Script + AI: Pilih Mana? | G13: Battle Build: 2 Tools, 1 Aplikasi | H13: 2 | I13: 140 | J13: Tentukan signature format final | K13: LOCKED: no additional long-form/live from revenue or membership calendar. Repurpose only.
A14: 13 | B14: 46384 | C14: 46390 | D14: 90-day recap + next season | E14: 90 Hari Membangun Channel AI: Apa yang Berhasil? | F14: Saya Bikin Aplikasi Wali Kelas Tanpa Jadi Programmer | G14: Final Build: Aplikasi Wali Kelas | H14: 2 | I14: 160 | J14: Audit 90 hari + plan Q4 berikutnya | K14: LOCKED: no additional long-form/live from revenue or membership calendar. Repurpose only.

Sheet WA DISTRIBUTION
A1: Day | B1: Guru Mahir AI (Public/Warm) | C1: Aidukasi (Closed/Warmer) | D1: Purpose | E1: Typical CTA | F1: Do Not
A2: Monday | B2: Problem awareness / education | C2: Deeper problem framing | D2: Start weekly theme | E2: Soft: lihat resource | F2: Jangan hard sell
A3: Tuesday | B3: Share YouTube + insight | C3: Share YouTube + context | D3: Authority/proof | E3: Watch / discuss | F3: Jangan bikin konten baru
A4: Wednesday | B4: Free prompt/resource | C4: Free + deeper explanation | D4: Lead/member activation | E4: Free Member / resource | F4: Jangan gate semua hal
A5: Thursday | B5: Practical tutorial | C5: Deep workflow + offer | D5: Education → conversion | E5: Premium/product | F5: Jangan spam
A6: Friday | B6: Share YouTube + case | C6: Case study / proof | D6: Authority + trust | E6: Product contextual | F6: Jangan broadcast semua segment
A7: Saturday | B7: Resource / checklist | C7: Resource + reminder | D7: Utility/retention | E7: Free/Premium | F7: Jangan over-post
A8: Sunday | B8: Live reminder + follow-up | C8: Live + next-step resource | D8: Engagement | E8: Join Live / member area | F8: Jangan jualan keras

Sheet KPI DASHBOARD
A1: KPI DASHBOARD — MASTER CONTENT OPERATING SYSTEM
A3: Metric | B3: Target / Rule | C3: Actual | D3: Status | E3: Notes
A4: Net Revenue / 30D | B4: From revenue roadmap | E4: North Star
A5: Daily Product Content | B5: >=1 post/day | E5: TikTok + Threads
A6: YT Long-form | B6: 2/week | E6: Tue + Fri
A7: YT Live | B7: 1/week | E7: Sun
A8: YT Shorts | B8: 2/week | E8: Wed + Sat
A9: Sumber Belajar derived | B9: 2–4/week | E9: Do not overproduce
A10: Signature asset | B10: <=1/week | E10: Only if workload safe
A11: WA touchpoints | B11: 5–7/week | E11: Segmented by pool
A12: Free → Premium | B12: Track conversion | E12: Membership
A13: Premium → VIP | B13: Track conversion | E13: Membership
A14: Apps shipped/shared | B14: Track by week | E14: Public/Free/Premium/VIP

Sheet SOURCE REVENUE
A1: 90-DAY REVENUE ROADMAP
A2: Tanggal diselaraskan dengan YouTube Growth Plan; revenue roadmap tidak menambah kewajiban upload YouTube.
A4: Week | B4: Mulai | C4: Selesai | D4: Fase | E4: Fokus Revenue | F4: Primary Campaign | G4: Audience Utama | H4: Key Revenue Action | I4: Affiliate Action | J4: WA / Lead Action | K4: Koordinasi YouTube (NO OVERLAP) | L4: Net Target / Minggu | M4: Gross Target / Minggu | N4: Status
A5: 1 | B5: 46300 | C5: 46306 | D5: Fase 1 | E5: Reset & tracking | F5: Post & Cuan reset + segmentasi | G5: Seluruh customer existing | H5: Backfill uang Juli–Agustus seperlunya; segmentasi ModulAjar/BuatSoal; promo Merdeka selesai 17 Agu. | I5: Audit affiliate aktif; jangan rekrut besar dulu. | J5: Tidak jualan keras 18 Agu; rapikan segment & next campaign. | K5: Ikuti YT Plan Week 1. Revenue hanya pasang CTA/lead magnet pada aset yang memang dibuat. | L5: 2450000 | M5: =(L5+(Dashboard!$B$16/Dashboard!$B$6*7))/Dashboard!$B$17 | N5: Planned
A6: 2 | B6: 46307 | C6: 46313 | D6: Fase 1 | E6: Cross-sell #1 | F6: ModulAjar → BuatSoal | G6: ModulAjar-only | H6: Campaign edukasi: setelah modul selesai, lanjut ke asesmen. Offer BuatSoal normal price. | I6: Affiliate fokus ModulAjar/BuatSoal; beri angle problem-solution. | J6: WA sequence 4–5 sentuhan: edukasi → demo → proof → offer. | K6: Gunakan output YT minggu ini sebagai proof/repurpose bila relevan; jangan buat video YouTube tambahan. | L6: 2450000 | M6: =(L6+(Dashboard!$B$16/Dashboard!$B$6*7))/Dashboard!$B$17 | N6: Planned
A7: 3 | B7: 46314 | C7: 46320 | D7: Fase 1 | E7: Acquisition sprint | F7: Lead magnet masuk WA | G7: Cold/warm audience baru | H7: Aktifkan 1 lead magnet high-intent dan tracking sumber lead. | I7: Minta affiliate kirim traffic ke hero product / lead asset yang disepakati. | J7: TikTok/Threads → lead magnet → Guru Mahir AI. | K7: YouTube tetap mengikuti plan. Potong/reuse aset YT untuk TikTok/Threads, bukan produksi topik baru. | L7: 2450000 | M7: =(L7+(Dashboard!$B$16/Dashboard!$B$6*7))/Dashboard!$B$17 | N7: Planned
A8: 4 | B8: 46321 | C8: 46327 | D8: Fase 1 | E8: Upgrade campaign | F8: BuatSoal Pro → Max | G8: ±100 user Pro | H8: Offer upgrade bayar selisih jika arsitektur produk memungkinkan; target 15–20 upgrade. | I8: Affiliate tidak jadi fokus utama untuk upgrade existing buyer. | J8: FAQ + demo pembeda Pro vs Max + CTA upgrade. | K8: Jangan jadwalkan live/video YT tambahan; gunakan demo yang sudah ada. | L8: 2450000 | M8: =(L8+(Dashboard!$B$16/Dashboard!$B$6*7))/Dashboard!$B$17 | N8: Planned
A9: 5 | B9: 46328 | C9: 46334 | D9: Fase 2 | E9: Lead Magnet Engine | F9: 2 jalur lead magnet | G9: Audience baru | H9: Pisahkan lead magnet ModulAjar vs BuatSoal agar intent lebih jelas. | I9: Berikan affiliate landing/angle khusus per hero product. | J9: Target +150–200 lead baru/bulan mulai fase ini. | K9: YT = discovery/authority. Revenue workbook hanya menentukan destination CTA. | L9: 2975000 | M9: =(L9+(Dashboard!$B$16/Dashboard!$B$6*7))/Dashboard!$B$17 | N9: Planned
A10: 6 | B10: 46335 | C10: 46341 | D10: Fase 2 | E10: Affiliate Sprint #1 | F10: Hero Week: ModulAjar | G10: Affiliate existing | H10: Target affiliate aktif ≥5; ukur sales/active affiliate dan new-customer rate. | I10: Brief mingguan ModulAjar + kit + leaderboard sederhana. | J10: WA grup affiliate: 1 briefing utama + 1 follow-up hasil. | K10: Tidak perlu konten YT khusus affiliate; gunakan materi dari YouTube plan sebagai sales asset. | L10: 2975000 | M10: =(L10+(Dashboard!$B$16/Dashboard!$B$6*7))/Dashboard!$B$17 | N10: Planned
A11: 7 | B11: 46342 | C11: 46348 | D11: Fase 2 | E11: Normal-price campaign | F11: BuatSoal Online | G11: Guru butuh asesmen/soal | H11: Campaign normal price berbasis demo, use case, testimonial, bukan diskon. | I11: Hero Week: BuatSoal. | J11: Lead magnet BuatSoal + case study + offer. | K11: YT Plan tetap punya kalendernya sendiri; revenue hanya bridge ke produk/lead magnet. | L11: 2975000 | M11: =(L11+(Dashboard!$B$16/Dashboard!$B$6*7))/Dashboard!$B$17 | N11: Planned
A12: 8 | B12: 46349 | C12: 46355 | D12: Fase 2 | E12: Normal-price campaign | F12: ModulAjar Online | G12: Guru butuh perencanaan | H12: Campaign normal price ModulAjar; audit CTA dan conversion dari WA. | I12: Hero Week: ModulAjar. | J12: Nurture lead baru + proof existing customer. | K12: Repurpose insight dari YT; tidak membuat long-form/live tambahan. | L12: 2975000 | M12: =(L12+(Dashboard!$B$16/Dashboard!$B$6*7))/Dashboard!$B$17 | N12: Planned
A13: 9 | B13: 46356 | C13: 46362 | D13: Fase 3 | E13: Scale winner | F13: Scale channel/campaign terbaik | G13: Segment dengan conversion tertinggi | H13: Double down hanya pada channel + offer yang terbukti 8 minggu pertama. | I13: Affiliate target aktif 10–15. | J13: Kurangi aktivitas yang tidak menghasilkan lead/sales. | K13: Gunakan cluster pemenang YT sebagai sumber konten lintas channel. | L13: 3500000 | M13: =(L13+(Dashboard!$B$16/Dashboard!$B$6*7))/Dashboard!$B$17 | N13: Planned
A14: 10 | B14: 46363 | C14: 46369 | D14: Fase 3 | E14: Affiliate Sprint #2 | F14: Hero Week: BuatSoal | G14: Affiliate + audience baru | H14: Dorong affiliate new-customer acquisition; ukur gross vs net setelah komisi. | I14: Target 10–15 affiliate aktif; coaching top performer. | J14: WA affiliate fokus objection handling + proof. | K14: Tidak menambah video YT. Materi YT hanya masuk marketing kit jika relevan. | L14: 3500000 | M14: =(L14+(Dashboard!$B$16/Dashboard!$B$6*7))/Dashboard!$B$17 | N14: Planned
A15: 11 | B15: 46370 | C15: 46376 | D15: Fase 3 | E15: Cross-sell #2 | F15: BuatSoal → ModulAjar | G15: BuatSoal-only | H15: Reverse cross-sell ke customer yang belum punya ModulAjar. | I15: Affiliate tetap hero-product campaign; cross-sell existing dilakukan direct. | J15: Segmented WA/DM; hindari broadcast ke semua orang. | K15: Gunakan konten YT sebagai authority; offer dilakukan di owned channel. | L15: 3500000 | M15: =(L15+(Dashboard!$B$16/Dashboard!$B$6*7))/Dashboard!$B$17 | N15: Planned
A16: 12 | B16: 46377 | C16: 46383 | D16: Fase 3 | E16: Backend validation | F16: Membership 9K + produk pendamping | G16: Buyer paling loyal | H16: Validasi membership 9K sebagai retention layer; produk lain sebagai backend, bukan hero. | I16: Ajak customer loyal yang cocok menjadi affiliate/advocate. | J16: Target 25–50 member aktif, tapi jangan korbankan hero-product sales. | K16: YouTube tetap fokus growth plan; membership hanya CTA opsional jika konteksnya cocok. | L16: 3500000 | M16: =(L16+(Dashboard!$B$16/Dashboard!$B$6*7))/Dashboard!$B$17 | N16: Planned
A17: 13 | B17: 46384 | C17: 46390 | D17: Fase 3 | E17: 90-day scale decision | F17: 500K/day run-rate | G17: Semua winning segment | H17: Audit 90 hari: revenue mix, channel, customer baru, affiliate, campaign winner. Tetapkan Q4. | I17: Target affiliate aktif 20+ bila kualitas pipeline mendukung. | J17: Pilih 1–2 engine untuk scale berikutnya; hentikan aktivitas low-ROI. | K17: Review bersama KPI YouTube, tetapi roadmap Q4 tetap memisahkan tujuan growth vs revenue. | L17: 3500000 | M17: =(L17+(Dashboard!$B$16/Dashboard!$B$6*7))/Dashboard!$B$17 | N17: Planned

Sheet SOURCE YOUTUBE
A1: Week | B1: Mulai | C1: Selesai | D1: Fase | E1: Fokus Mingguan | F1: Long-form #1 | G1: Long-form #2 | H1: LIVE | I1: Shorts | J1: Target Watch Hours | K1: Review Mingguan | L1: Status
A2: 1 | B2: 05/10/2026 | C2: 11/10/2026 | D2: Repositioning | E2: Reset positioning + bangun cluster Gemini/Deploy | F2: Gemini Canvas ke Netlify: Cara Deploy Website Sampai Online | G2: Saya Bikin Aplikasi Tanpa Bisa Coding — Ini Workflow Saya | H2: Bikin Web App dari Nol dengan AI + Deploy | I2: 2 | J2: 25 | K2: Cek CTR + retention 30 detik | L2: Planned
A3: 2 | B3: 12/10/2026 | C3: 18/10/2026 | D3: Repositioning | E3: Custom GPT cluster | F3: Cara Membuat Custom GPT dari Nol — Sampai Bisa Dipakai | G3: 7 Kesalahan Saat Membuat Custom GPT | H3: Bikin Custom GPT untuk Membuat Soal | I3: 2 | J3: 30 | K3: Bandingkan search vs browse | L3: Planned
A4: 3 | B4: 19/10/2026 | C4: 25/10/2026 | D4: Repositioning | E4: PRD → aplikasi | F4: Dari Ide → PRD → Aplikasi dengan AI | G4: Tools AI Pembuat PRD: Saya Tes untuk Project Nyata | H4: Dari Ide Kosong Jadi PRD + Prototype | I4: 2 | J4: 35 | K4: Catat pertanyaan audience | L4: Planned
A5: 4 | B5: 26/10/2026 | C5: 01/11/2026 | D5: Repositioning | E5: Guru Bikin Aplikasi dimulai | F5: Saya Bikin Aplikasi Absensi Siswa Pakai AI | G5: Google Sheets Jadi Aplikasi dalam 30 Menit | H5: Bikin Aplikasi Absensi Siswa dari Nol | I5: 2 | J5: 40 | K5: Pilih 2 cluster terbaik bulan 1 | L5: Planned
A6: 5 | B6: 02/11/2026 | C6: 08/11/2026 | D6: Double Down | E6: Scale cluster pemenang + nilai siswa | F6: Saya Bikin Aplikasi Nilai Siswa Pakai AI | G6: Cara Update Website Netlify Tanpa Ganti Link | H6: Bikin Aplikasi Nilai + Rekap Otomatis | I6: 2 | J6: 50 | K6: Update thumbnail video CTR rendah | L6: Planned
A7: 6 | B7: 09/11/2026 | C7: 15/11/2026 | D7: Double Down | E7: Gemini Gems + workflow guru | F7: Cara Membuat Gemini Gems yang Benar | G7: Saya Bikin AI Pembuat Soal dengan Gemini Gems | H7: Bikin Asisten Soal Guru dengan Gemini | I7: 2 | J7: 60 | K7: Perkuat end-screen chain | L7: Planned
A8: 7 | B8: 16/11/2026 | C8: 22/11/2026 | D8: Double Down | E8: Deploy + domain | F8: Cara Pasang Custom Domain di Netlify untuk Pemula | G8: Netlify vs Vercel: Mana Paling Mudah untuk Pemula? | H8: Web AI → Deploy → Custom Domain LIVE | I8: 2 | J8: 70 | K8: Cek suggested traffic antarvideo | L8: Planned
A9: 8 | B9: 23/11/2026 | C9: 29/11/2026 | D9: Double Down | E9: AI productivity + education crossover | F9: Dari RPP Jadi PowerPoint dengan AI | G9: 7 Prompt AI yang Menghemat Pekerjaan Guru | H9: Bikin Media Pembelajaran dari RPP | I9: 2 | J9: 80 | K9: Review 8 minggu: stop topik lemah | L9: Planned
A10: 9 | B10: 30/11/2026 | C10: 06/12/2026 | D10: Series Engine | E10: Serial Guru Bikin Aplikasi | F10: Bikin Aplikasi Kas Kelas dengan AI | G10: Bikin Aplikasi Jurnal Mengajar dengan AI | H10: Bikin Kas Kelas + Dashboard | I10: 2 | J10: 95 | K10: Optimasi playlist series | L10: Planned
A11: 10 | B11: 07/12/2026 | C11: 13/12/2026 | D11: Series Engine | E11: Build in public produk nyata | F11: Saya Bikin PosterEdu: Dari Masalah Jadi Aplikasi | G11: Kenapa Aplikasi AI Saya Lambat? Ini Kesalahannya | H11: Audit + Perbaiki Aplikasi AI yang Lambat | I11: 2 | J11: 110 | K11: Cari peak retention untuk format authority | L11: Planned
A12: 11 | B12: 14/12/2026 | C12: 20/12/2026 | D12: Series Engine | E12: Marketplace / produk digital | F12: Dari Aplikasi Jadi Produk Digital: Workflow Saya | G12: Saya Tambahkan Marketplace ke Aplikasi Guru | H12: Build Marketplace Sederhana dengan AI | I12: 2 | J12: 125 | K12: Periksa subscriber gained/video | L12: Planned
A13: 12 | B13: 21/12/2026 | C13: 27/12/2026 | D13: Series Engine | E13: Perbandingan tools berintent tinggi | F13: ChatGPT vs Gemini untuk Bikin Aplikasi: Saya Tes | G13: Lovable vs Google Apps Script + AI: Pilih Mana? | H13: Battle Build: 2 Tools, 1 Aplikasi | I13: 2 | J13: 140 | K13: Tentukan signature format final | L13: Planned
A14: 13 | B14: 28/12/2026 | C14: 03/01/2027 | D14: Series Engine | E14: 90-day recap + next season | F14: 90 Hari Membangun Channel AI: Apa yang Berhasil? | G14: Saya Bikin Aplikasi Wali Kelas Tanpa Jadi Programmer | H14: Final Build: Aplikasi Wali Kelas | I14: 2 | J14: 160 | K14: Audit 90 hari + plan Q4 berikutnya | L14: Planned
